fyers_logger.py
fyers_logger-0.1.7.dist-info/METADATA
fyers_logger-0.1.7.dist-info/WHEEL
fyers_logger-0.1.7.dist-info/top_level.txt
fyers_logger-0.1.7.dist-info/RECORD
