Metadata-Version: 2.1
Name: fyers-logger
Version: 0.1.7
Summary: Fyers Internal Logging Library
Home-page: https://github.com/FyersDev/fyers-logger
Author: Fyers-Tech
Author-email: support@fyers.in
License: UNKNOWN
Platform: UNKNOWN
Classifier: Programming Language :: Python :: 3
Classifier: License :: OSI Approved :: MIT License
Classifier: Operating System :: OS Independent
Requires-Python: >=3.8
Requires-Dist: aws-lambda-powertools (==1.25.5)
